shfuncdecfmt/__init__.py
shfuncdecfmt-1.0.1.dist-info/METADATA
shfuncdecfmt-1.0.1.dist-info/WHEEL
shfuncdecfmt-1.0.1.dist-info/entry_points.txt
shfuncdecfmt-1.0.1.dist-info/licenses/LICENSE
shfuncdecfmt-1.0.1.dist-info/RECORD
